recognite/__init__.py
recognite/data/__init__.py
recognite/data/data_frame_dataset.py
recognite/data/gallery_query_split.py
recognite/data/k_fold.py
recognite/data/train_val_datasets.py
recognite/eval/__init__.py
recognite/eval/accuracy.py
recognite/eval/hard_pos_neg_scores.py
recognite/eval/knn.py
recognite/eval/pr_metrics.py
recognite/eval/score_matrix.py
recognite/model/__init__.py
recognite/model/classifier_ops.py
recognite/model/recognizer.py
recognite/utils/__init__.py
recognite/utils/avg_ref_embs.py
recognite/utils/running_extrema.py
recognite/utils/three_crop.py
recognite-0.1.1.dist-info/LICENSE
recognite-0.1.1.dist-info/METADATA
recognite-0.1.1.dist-info/WHEEL
recognite-0.1.1.dist-info/top_level.txt
recognite-0.1.1.dist-info/RECORD
